setup.py
json_escape/__init__.py
json_escape/json_escape.py
json_escape.egg-info/PKG-INFO
json_escape.egg-info/SOURCES.txt
json_escape.egg-info/dependency_links.txt
json_escape.egg-info/entry_points.txt
json_escape.egg-info/requires.txt
json_escape.egg-info/top_level.txt