Metadata-Version: 1.1
Name: json-escape
Version: 1.0.0
Summary: Json escape
Home-page: UNKNOWN
Author: Alexandru Obada
Author-email: UNKNOWN
License: UNKNOWN
Platform: UNKNOWN
Classifier: Development Status :: 3 - Alpha
Classifier: Intended Audience :: Developers
Classifier: License :: OSI Approved :: MIT License
Classifier: Programming Language :: Python :: 3.6
